{
  "$schema": "https://frontmatter.codes/frontmatter.schema.json",
  "frontMatter.taxonomy.contentTypes": [
    {
      "name": "default",
      "pageBundle": false,
      "fields": [
        {
          "title": "title",
          "name": "title",
          "type": "string"
        },
        {
          "title": "date",
          "name": "date",
          "type": "datetime"
        },
        {
          "title": "update",
          "name": "update",
          "type": "datetime"
        },
        {
          "title": "authors",
          "name": "authors",
          "type": "string"
        },
        {
          "title": "tags",
          "name": "tags",
          "type": "tags"
        },
        {
          "title": "keywords",
          "name": "keywords",
          "type": "choice",
          "choices": ["计算机技术", "工具", "项目管理", "开源"]
        },
        {
          "title": "description",
          "name": "description",
          "type": "string"
        },
        {
          "title": "meta_title",
          "name": "meta_title",
          "type": "string"
        },
        {
          "title": "categories",
          "name": "categories",
          "type": "categories"
        },
        {
          "title": "author",
          "name": "author",
          "type": "string"
        },
        {
          "title": "draft",
          "name": "draft",
          "type": "draft"
        }
      ]
    }
  ]
}
